<?xml version="1.0"?>
<import>
  <ConditionLookup public-id="z3ngkg07jrdqp65t194eicksa5b">
    <Availability>Available</Availability>
    <ConditionPatternCode>WC7EmployeeLeasingCompanyClientTerminationEndorsementCond</ConditionPatternCode>
    <EndEffectiveDate/>
    <JobType>PolicyChange</JobType>
    <PolicyLinePatternCode>WC7Line</PolicyLinePatternCode>
    <StartEffectiveDate>2014-01-01 00:00:00.000</StartEffectiveDate>
    <State>WI</State>
    <UWCompanyCode/>
  </ConditionLookup>
  <ConditionLookup public-id="zdbh0fp7g1mn81enc1156o198ra">
    <Availability>Available</Availability>
    <ConditionPatternCode>WC7EmployeeLeasingCompanyClientTerminationEndorsementCond</ConditionPatternCode>
    <EndEffectiveDate/>
    <JobType>Rewrite</JobType>
    <PolicyLinePatternCode>WC7Line</PolicyLinePatternCode>
    <StartEffectiveDate>2014-01-01 00:00:00.000</StartEffectiveDate>
    <State>WI</State>
    <UWCompanyCode/>
  </ConditionLookup>
</import>